mail_cleaner/__init__.py
mail_cleaner/apps.py
mail_cleaner/constants.py
mail_cleaner/mail.py
mail_cleaner/py.typed
mail_cleaner/sanitizer.py
mail_cleaner/text.py
mail_cleaner/utils.py
mail_cleaner-2.0.0.dist-info/licenses/LICENSE
mail_cleaner-2.0.0.dist-info/METADATA
mail_cleaner-2.0.0.dist-info/WHEEL
mail_cleaner-2.0.0.dist-info/top_level.txt
mail_cleaner-2.0.0.dist-info/RECORD
